mdps_ds_lib/__init__.py
mdps_ds_lib/ds_client/__init__.py
mdps_ds_lib/ds_client/auth_token/__init__.py
mdps_ds_lib/ds_client/auth_token/token_abstract.py
mdps_ds_lib/ds_client/auth_token/token_cognito.py
mdps_ds_lib/ds_client/auth_token/token_dummy.py
mdps_ds_lib/ds_client/auth_token/token_factory.py
mdps_ds_lib/ds_client/ds_client_admin.py
mdps_ds_lib/ds_client/ds_client_base.py
mdps_ds_lib/ds_client/ds_client_user.py
mdps_ds_lib/lib/__init__.py
mdps_ds_lib/lib/aws/__init__.py
mdps_ds_lib/lib/aws/aws_cognito.py
mdps_ds_lib/lib/aws/aws_cred.py
mdps_ds_lib/lib/aws/aws_lambda.py
mdps_ds_lib/lib/aws/aws_message_transformers.py
mdps_ds_lib/lib/aws/aws_param_store.py
mdps_ds_lib/lib/aws/aws_s3.py
mdps_ds_lib/lib/aws/aws_sns.py
mdps_ds_lib/lib/aws/es_abstract.py
mdps_ds_lib/lib/aws/es_factory.py
mdps_ds_lib/lib/aws/es_middleware_abstract.py
mdps_ds_lib/lib/aws/es_middleware_aws.py
mdps_ds_lib/lib/aws/es_middleware_no_auth.py
mdps_ds_lib/lib/aws/os_middleware_aws.py
mdps_ds_lib/lib/cognito_login/__init__.py
mdps_ds_lib/lib/cognito_login/cognito_login.py
mdps_ds_lib/lib/cognito_login/cognito_token_retriever.py
mdps_ds_lib/lib/constants.py
mdps_ds_lib/lib/cumulus_stac/__init__.py
mdps_ds_lib/lib/cumulus_stac/collection_transformer.py
mdps_ds_lib/lib/cumulus_stac/granules_catalog.py
mdps_ds_lib/lib/cumulus_stac/item_transformer.py
mdps_ds_lib/lib/cumulus_stac/stac_transformer_abstract.py
mdps_ds_lib/lib/cumulus_stac/stac_utils.py
mdps_ds_lib/lib/cumulus_stac/unity_collection_stac.py
mdps_ds_lib/lib/earthdata_login/__init__.py
mdps_ds_lib/lib/earthdata_login/urs_token.py
mdps_ds_lib/lib/earthdata_login/urs_token_retriever.py
mdps_ds_lib/lib/processing_jobs/__init__.py
mdps_ds_lib/lib/processing_jobs/job_executor_abstract.py
mdps_ds_lib/lib/processing_jobs/job_manager_abstract.py
mdps_ds_lib/lib/processing_jobs/job_manager_factory.py
mdps_ds_lib/lib/processing_jobs/job_manager_local_filesystem.py
mdps_ds_lib/lib/processing_jobs/job_manager_memory.py
mdps_ds_lib-1.2.0.dist-info/METADATA
mdps_ds_lib-1.2.0.dist-info/WHEEL
mdps_ds_lib-1.2.0.dist-info/licenses/LICENSE
mdps_ds_lib-1.2.0.dist-info/RECORD
