Metadata-Version: 2.4
Name: mdps-ds-lib
Version: 1.2.0
Summary: Mission Data System - MDPS (Unity) Data Service Core library
License: Apache 2.0
License-File: LICENSE
Author: Wai Phyo
Author-email: wai.phyo@jpl.nasa.gov
Requires-Python: >=3.9,<4.0
Classifier: License :: OSI Approved :: Apache Software License
Classifier: License :: Other/Proprietary License
Classifier: Operating System :: OS Independent
Classifier: Programming Language :: Python :: 3
Classifier: Programming Language :: Python :: 3.9
Classifier: Programming Language :: Python :: 3.10
Classifier: Programming Language :: Python :: 3.11
Classifier: Programming Language :: Python :: 3.12
Classifier: Programming Language :: Python :: 3.13
Classifier: Programming Language :: Python :: 3.14
Requires-Dist: boto3 (>=1.36.11,<2.0.0)
Requires-Dist: fastjsonschema (>=2.19.1,<3.0.0)
Requires-Dist: jsonschema (>=4.23.0,<5.0.0)
Requires-Dist: opensearch-py (>=3.0.0,<4.0.0)
Requires-Dist: pystac (==1.9.0)
Requires-Dist: python-dotenv (>=1.0.1,<2.0.0)
Requires-Dist: requests-aws4auth (==1.2.3)
Requires-Dist: tenacity (==8.2.3)
Requires-Dist: xmltodict (==0.13.0)
Project-URL: Homepage, https://github.com/unity-sds/sampleproject
Project-URL: Issues, https://github.com/unity-sds/sampleproject/issues
